[
  {"abandon": "ত্যাগ করা"},
  {"absolute": "পরম"},
  {"absolutely": "সম্পূর্ণভাবে"},
  {"absorb": "শোষণ করা"},
  {"academic": "একাডেমিক"},
  {"accept": "গ্রহণ করা"},
  {"acceptable": "গ্রহণযোগ্য"},
  {"access": "অ্যাক্সেস"},
  {"accidental": "দুর্ঘটনাজনিত"},
  {"accommodate": "সমন্বয় করা"},
  {"accompany": "সহগমন করা"},
  {"accurate": "সঠিক"},
  {"accuse": "অভিযোগ করা"},
  {"achieve": "অর্জন করা"},
  {"achievement": "অর্জন"},
  {"acknowledge": "স্বীকার করা"},
  {"acquire": "অর্জন করা"},
  {"additional": "অতিরিক্ত"},
  {"adequate": "যথেষ্ট"},
  {"adjust": "সমন্বয় করা"},
  {"admire": "প্রশংসা করা"},
  {"adopt": "দত্তক নেওয়া/গ্রহণ করা"},
  {"advanced": "উন্নত"},
  {"advantage": "সুবিধা"},
  {"adventure": "অ্যাডভেঞ্চার"},
  {"advertise": "বিজ্ঞাপন দেওয়া"},
  {"advice": "পরামর্শ"},
  {"affection": "স্নেহ"},
  {"afford": "সক্ষম হওয়া"},
  {"aggressive": "আক্রমণাত্মক"},
  {"agreement": "চুক্তি"},
  {"alternative": "বিকল্প"},
  {"amazing": "অসাধারণ"},
  {"ambition": "আকাঙ্ক্ষা"},
  {"analyze": "বিশ্লেষণ করা"},
  {"analysis": "বিশ্লেষণ"},
  {"ancient": "প্রাচীন"},
  {"announce": "ঘোষণা করা"},
  {"annual": "বার্ষিক"},
  {"anticipate": "অপেক্ষা করা"},
  {"anxiety": "উদ্বেগ"},
  {"apologize": "ক্ষমা চাওয়া"},
  {"apparent": "স্পষ্ট"},
  {"appeal": "আবেদন"},
  {"application": "আবেদন"},
  {"appreciate": "মূল্যায়ন করা"},
  {"appropriate": "উপযুক্ত"},
  {"approval": "অনুমোদন"},
  {"approximate": "আনুমানিক"},
  {"argue": "তর্ক করা"},
  {"arrangement": "ব্যবস্থা"},
  {"artificial": "কৃত্রিম"},
  {"artist": "শিল্পী"},
  {"artistic": "শৈল্পিক"},
  {"ashamed": "লজ্জিত"},
  {"aspect": "পক্ষ"},
  {"assist": "সহায়তা করা"},
  {"associate": "সহযোগী"},
  {"assume": "অনুমান করা"},
  {"assure": "আশ্বস্ত করা"},
  {"atmosphere": "বায়ুমণ্ডল"},
  {"attach": "সংযুক্ত করা"},
  {"attack": "আক্রমণ করা"},
  {"attempt": "প্রচেষ্টা"},
  {"attention": "মনোযোগ"},
  {"attitude": "মানসিকতা"},
  {"authority": "কর্তৃত্ব"},
  {"available": "উপলব্ধ"},
  {"average": "গড়"},
  {"avoid": "পরিহার করা"},
  {"aware": "সচেতন"},
  {"awkward": "বেমানান"},
  {"awkwardly": "বেমানানভাবে"},
  {"attraction": "আকর্ষণ"},
  {"attractive": "আকর্ষণীয়"},
  {"audience": "শ্রোতাগণ"},
  {"authority": "কর্তৃত্ব"},
  {"accurate": "সঠিক"},
  {"alarming": "উদ্বেগজনক"},
  {"alternative": "বিকল্প"},
  {"approximately": "আনুমানিকভাবে"},
  {"balance": "ভারসাম্য"},
  {"ban": "নিষেধাজ্ঞা"},
  {"bargain": "দর কষাকষি"},
  {"barrier": "বাধা"},
  {"basically": "মোটের উপর"},
  {"behavior": "আচরণ"},
  {"benefit": "সুবিধা"},
  {"belief": "বিশ্বাস"},
  {"belong": "অধিকারভুক্ত হওয়া"},
  {"border": "সীমান্ত"},
  {"brain": "মস্তিষ্ক"},
  {"brilliant": "দুর্দান্ত"},
  {"broadcast": "সম্প্রচার"},
  {"budget": "বাজেট"},
  {"business": "ব্যবসা"},
  {"capable": "সক্ষম"},
  {"capacity": "ধারণক্ষমতা"},
  {"career": "পেশা"},
  {"celebrate": "উদযাপন করা"},
  {"celebration": "উদযাপন"},
  {"certificate": "সার্টিফিকেট"},
  {"challenge": "চ্যালেঞ্জ"},
  {"characteristic": "বৈশিষ্ট্য"},
  {"chemistry": "রাসায়নিক বিদ্যা"},
  {"citizen": "নাগরিক"},
  {"climate": "আবহাওয়া"},
  {"colleague": "সহকর্মী"},
  {"combination": "সমন্বয়"},
  {"committee": "কমিটি"},
  {"communicate": "যোগাযোগ করা"},
  {"communication": "যোগাযোগ"},
  {"community": "সমাজ"},
  {"competitive": "প্রতিযোগিতামূলক"},
  {"concentrate": "মনোযোগ কেন্দ্রীভূত করা"},
  {"conclusion": "উপসংহার"},
  {"confidence": "আত্মবিশ্বাস"},
  {"connection": "সংযোগ"},
  {"consequence": "ফলাফল"},
  {"considerable": "গুরুত্বপূর্ণ"},
  {"contribution": "অবদান"},
  {"Convention": "রীতি"},
  {"convenient": "সুবিধাজনক"},
  {"customer": "গ্রাহক"},
  {"data": "ডেটা"},
  {"debate": "বিতর্ক"},
  {"debt": "ঋণ"},
  {"decade": "দশক"},
  {"decision": "সিদ্ধান্ত"},
  {"declare": "ঘোষণা করা"},
  {"decrease": "হ্রাস করা"},
  {"defeat": "পরাজিত করা"},
  {"define": "সংজ্ঞায়িত করা"},
  {"definitely": "নিশ্চিতভাবে"},
  {"definition": "সংজ্ঞা"},
  {"delicate": "সুকুমার"},
  {"deliver": "সরবরাহ করা"},
  {"demand": "চাহিদা"},
  {"demonstrate": "প্রদর্শন করা"},
  {"department": "বিভাগ"},
  {"departure": "বিদায়"},
  {"depend": "নির্ভর করা"},
  {"deposit": "জমা"},
  {"describe": "বর্ণনা করা"},
  {"description": "বর্ণনা"},
  {"deserve": "প্রাপ্য হওয়া"},
  {"design": "নকশা"},
  {"desperate": "হতাশাগ্রস্ত"},
  {"destroy": "ধ্বংস করা"},
  {"destruction": "ধ্বংস"},
  {"detail": "বিস্তারিত"},
  {"determination": "সংকল্প"},
  {"determined": "সঙ্কল্পবদ্ধ"},
  {"develop": "উন্নত করা"},
  {"development": "উন্নয়ন"},
  {"device": "যন্ত্র"},
  {"devote": "উৎসর্গ করা"},
  {"dictionary": "অভিধান"},
  {"difference": "পার্থক্য"},
  {"difficult": "কঠিন"},
  {"disadvantage": "অসুবিধা"},
  {"discuss": "আলোচনা করা"},
  {"discussion": "আলোচনা"},
  {"disease": "রোগ"},
  {"distribute": "বণ্টন করা"},
  {"District": "জেলা"},
  {"distance": "দূরত্ব"},
  {"economic": "অর্থনৈতিক"},
  {"economy": "অর্থনীতি"},
  {"edge": "কিনারা"},
  {"edition": "সংস্করণ"},
  {"educate": "শিক্ষা দেওয়া"},
  {"education": "শিক্ষা"},
  {"effect": "প্রভাব"},
  {"effective": "কার্যকর"},
  {"effectively": "কার্যকরভাবে"},
  {"efficient": "দক্ষ"},
  {"efficiently": "দক্ষতার সাথে"},
  {"effort": "প্রয়াস"},
  {"election": "নির্বাচন"},
  {"electric": "বৈদ্যুতিক"},
  {"electrical": "বৈদ্যুতিক"},
  {"electronic": "ইলেকট্রনিক"},
  {"elegant": "রুচিসম্মত"},
  {"emergency": "জরুরি"},
  {"emotion": "ভাবাবেগ"},
  {"emotional": "আবেগপ্রবণ"},
  {"emphasis": "গুরুত্ব"},
  {"emphasize": "গুরুত্ব দেওয়া"},
  {"employ": "চাকরি দেওয়া"},
  {"employee": "কর্মচারী"},
  {"employer": "কর্মদাতা"},
  {"employment": "চাকরি"},
  {"enable": "সক্ষম করা"},
  {"encounter": "মুখোমুখি হওয়া"},
  {"encourage": "উত্সাহ দেওয়া"},
  {"encouragement": "উত্সাহ"},
  {"energy": "শক্তি"},
  {"engaged": "সম্পৃক্ত"}
]
